music_manager-0.1a2.post2.dist-info/WHEEL
music_manager-0.1a2.post2.dist-info/DESCRIPTION.rst
music_manager-0.1a2.post2.dist-info/RECORD
music_manager-0.1a2.post2.dist-info/top_level.txt
music_manager-0.1a2.post2.dist-info/METADATA
music_manager-0.1a2.post2.dist-info/metadata.json
music_manager/Ui_GUI.py
music_manager/search.py
music_manager/myDragTable.py
music_manager/edit.py
music_manager/Ui_edit.py
music_manager/load.py
music_manager/genre.py
music_manager/Ui_genre.py
music_manager/GUI.py
music_manager/song.py
music_manager/main.py
music_manager/__init__.py
music_manager/mydockframe.py
music_manager/musicplayer.py
music_manager/resource_rc.py
music_manager/Ui_mplay.py
music_manager/myDropTable.py
music_manager/Ui_load.py
music_manager/Ui_info.py
music_manager/mylistview.py
music_manager/Ui_search.py
music_manager/mytreeview.py
music_manager/info.py
music_manager/Ui_musicplayer.py
music_manager/dbcreate.py
music_manager/myProgressbar.py
