Metadata-Version: 2.0
Name: music-manager
Version: 0.1a2.post2
Summary: Maintain and listen to your music
Home-page: https://github.com/cedi4155476/musicmanager
Author: Cedric Christen
Author-email: cedric_christen@bluewin.ch
License: MIT
Keywords: music manager
Platform: UNKNOWN
Classifier: Development Status :: 3 - Alpha
Classifier: Intended Audience :: End Users/Desktop
Classifier: Topic :: Multimedia :: Sound/Audio :: Players :: MP3
Classifier: License :: OSI Approved :: MIT License
Classifier: Programming Language :: Python :: 2.7
Requires-Dist: pyglet
Requires-Dist: python-magic
Requires-Dist: mutagen
